pokerFunctions/__init__.py
pokerFunctions/equity.py
pokerFunctions/gamebank.py
pokerFunctions/test_classes.py
pokerFunctions-0.6.dist-info/METADATA
pokerFunctions-0.6.dist-info/WHEEL
pokerFunctions-0.6.dist-info/top_level.txt
pokerFunctions-0.6.dist-info/RECORD
