Metadata-Version: 2.1
Name: pokerFunctions
Version: 0.6
Summary: A package for poker functions
Home-page: https://github.com/yourusername/pokerFunctions
Author: Jonah Aden
Author-email: your.email@example.com
Classifier: Programming Language :: Python :: 3
Classifier: License :: OSI Approved :: MIT License
Classifier: Operating System :: OS Independent
Requires-Python: >=3.6
